pyanchetto/__init__.py
pyanchetto/chess.py
pyanchetto/chess_parser.py
pyanchetto/driver.py
pyanchetto/move_tree.py
pyanchetto/perft.py
pyanchetto/pgn_interpreter.py
pyanchetto/pgn_parser.py
pyanchetto-0.3.0.dist-info/LICENSE
pyanchetto-0.3.0.dist-info/METADATA
pyanchetto-0.3.0.dist-info/WHEEL
pyanchetto-0.3.0.dist-info/top_level.txt
pyanchetto-0.3.0.dist-info/RECORD
