Metadata-Version: 2.1
Name: pyanchetto
Version: 0.3.0
Summary: A python chess engine.
Home-page: https://github.com/ewimberley/Pyanchetto
Author: Eric Wimberley
License: UNKNOWN
Project-URL: Bug Tracker, https://github.com/ewimberley/Pyanchetto/issues
Platform: UNKNOWN
Requires-Python: >=3.6
License-File: LICENSE
Requires-Dist: yarp-parser (>=0.2)
